setup.py
nim_types.egg-info/PKG-INFO
nim_types.egg-info/SOURCES.txt
nim_types.egg-info/dependency_links.txt
nim_types.egg-info/top_level.txt
ntypes/__init__.py