Metadata-Version: 1.0
Name: nim-types
Version: 0.3
Summary: ctypes interoperability with the Nim language
Home-page: https://github.com/subsetpark/ntypes
Author: Zach Smith
Author-email: subsetpark@gmail.com
License: BSD3
Platform: UNKNOWN
